wikifeet/__init__.py
wikifeet/feet_of_the_day.py
wikifeet/feet_of_the_week.py
wikifeet/feet_of_the_year.py
wikifeet/random_feet.py
wikifeet/wikifeet.py
wikifeet/wikifeet_country_stats.py
wikifeet/wikifeet_stats.py
wikifeet-1.0.0.dist-info/LICENSE
wikifeet-1.0.0.dist-info/METADATA
wikifeet-1.0.0.dist-info/WHEEL
wikifeet-1.0.0.dist-info/top_level.txt
wikifeet-1.0.0.dist-info/RECORD
