Metadata-Version: 2.1
Name: wikifeet
Version: 1.0.0
Summary: WikiFeet (The collaborative celebrity feet website) crawler
Home-page: https://github.com/sloppydaddy/wikifeet-py
Author: XXIV
License: UNKNOWN
Project-URL: Bug Tracker, https://github.com/sloppydaddy/wikifeet-py/issues
Platform: UNKNOWN
Classifier: Programming Language :: Python :: 3
Classifier: License :: OSI Approved :: Apache Software License
Classifier: Operating System :: OS Independent
Requires-Python: >=3.6
License-File: LICENSE
